rewardify/__init__.py
rewardify/_util.py
rewardify/_util_test.py
rewardify/adapters.py
rewardify/cli.py
rewardify/env.py
rewardify/main.py
rewardify/models.py
rewardify/password.py
rewardify/probability.py
rewardify/rarity.py
rewardify/backends/__init__.py
rewardify/backends/base.py
rewardify/backends/forest.py
rewardify/backends/mock.py
rewardify/templates/config.jinja2
rewardify/templates/test/config.jinja2
rewardify-0.2.12.dist-info/DESCRIPTION.rst
rewardify-0.2.12.dist-info/METADATA
rewardify-0.2.12.dist-info/RECORD
rewardify-0.2.12.dist-info/WHEEL
rewardify-0.2.12.dist-info/metadata.json
rewardify-0.2.12.dist-info/top_level.txt
